{
    "name": "Theme",
    "fields": [
        {
            "fieldName": "themeName",
            "fieldType": "String",
            "fieldValidateRules": [
                "required"
            ]
        },
        {
            "fieldName": "description",
            "fieldType": "String"
        }
    ],
    "relationships": [
        {
            "relationshipType": "many-to-many",
            "otherEntityName": "objectif",
            "otherEntityRelationshipName": "theme",
            "relationshipName": "objectif",
            "otherEntityField": "id",
            "ownerSide": true
        }
    ],
    "changelogDate": "20191220044434",
    "entityTableName": "theme",
    "dto": "no",
    "pagination": "pagination",
    "service": "no",
    "jpaMetamodelFiltering": false,
    "fluentMethods": true,
    "readOnly": false,
    "clientRootFolder": "",
    "applications": "*"
}